Metadata-Version: 1.0
Name: Bino-Gaus-distributions
Version: 0.1
Summary: Gaussian and Binomial distributions
Home-page: UNKNOWN
Author: Johnson Ayanda
Author-email: jayanda46@gmail.com
License: UNKNOWN
Platform: UNKNOWN
